steganographer/__init__.py
steganographer/__main__.py
steganographer/steganographer.py
steganographer-2.0.0.dist-info/top_level.txt
steganographer-2.0.0.dist-info/entry_points.txt
steganographer-2.0.0.dist-info/METADATA
steganographer-2.0.0.dist-info/DESCRIPTION.rst
steganographer-2.0.0.dist-info/metadata.json
steganographer-2.0.0.dist-info/WHEEL
steganographer-2.0.0.dist-info/RECORD
